simdict/__init__.py
simdict/core.py
simdict-0.1.1.dist-info/DESCRIPTION.rst
simdict-0.1.1.dist-info/METADATA
simdict-0.1.1.dist-info/RECORD
simdict-0.1.1.dist-info/WHEEL
simdict-0.1.1.dist-info/entry_points.txt
simdict-0.1.1.dist-info/metadata.json
simdict-0.1.1.dist-info/top_level.txt
