Metadata-Version: 1.0
Name: simdict
Version: 0.1.1
Summary: This is a simple English - Chinese dictionary
Home-page: https://github.com/4cat/simdict
Author: 4cat
Author-email: 4catcode@gmail.com
License: MIT
Keywords: dictionary
Platform: UNKNOWN
